odoo/addons/shopinvader_api_settings/README.rst
odoo/addons/shopinvader_api_settings/__init__.py
odoo/addons/shopinvader_api_settings/__manifest__.py
odoo/addons/shopinvader_api_settings/i18n/shopinvader_api_settings.pot
odoo/addons/shopinvader_api_settings/readme/CONTRIBUTORS.rst
odoo/addons/shopinvader_api_settings/readme/DESCRIPTION.rst
odoo/addons/shopinvader_api_settings/routers/__init__.py
odoo/addons/shopinvader_api_settings/routers/settings.py
odoo/addons/shopinvader_api_settings/schemas/__init__.py
odoo/addons/shopinvader_api_settings/schemas/country.py
odoo/addons/shopinvader_api_settings/schemas/lang.py
odoo/addons/shopinvader_api_settings/schemas/partner_title.py
odoo/addons/shopinvader_api_settings/schemas/settings.py
odoo/addons/shopinvader_api_settings/static/description/index.html
odoo/addons/shopinvader_api_settings/tests/__init__.py
odoo/addons/shopinvader_api_settings/tests/common.py
odoo/addons/shopinvader_api_settings/tests/test_shopinvader_settings_api.py
odoo_addon_shopinvader_api_settings-16.0.1.0.1.dist-info/METADATA
odoo_addon_shopinvader_api_settings-16.0.1.0.1.dist-info/WHEEL
odoo_addon_shopinvader_api_settings-16.0.1.0.1.dist-info/top_level.txt
odoo_addon_shopinvader_api_settings-16.0.1.0.1.dist-info/RECORD
